mkdocs_fun_plugin/__init__.py
mkdocs_fun_plugin/__main__.py
mkdocs_fun_plugin/plugin.py
mkdocs_fun_plugin/py.typed
mkdocs_fun_plugin-0.2.1.dist-info/METADATA
mkdocs_fun_plugin-0.2.1.dist-info/WHEEL
mkdocs_fun_plugin-0.2.1.dist-info/entry_points.txt
mkdocs_fun_plugin-0.2.1.dist-info/RECORD
