Metadata-Version: 2.4
Name: mkdocs-fun-plugin
Version: 0.2.1
Summary: Dead simple custom python functions with mkdocs
Project-URL: Homepage, https://github.com/gbbirkisson/mkdocs-fun-plugin
Project-URL: Documentation, https://github.com/gbbirkisson/mkdocs-fun-plugin
Project-URL: Repository, https://github.com/gbbirkisson/mkdocs-fun-plugin.git
Author-email: Guðmundur Björn Birkisson <gbb@gbb.is>
Requires-Python: >=3.9
Requires-Dist: mkdocs>=1.4
